solstar/__init__.py
solstar/aia_download_n_calib.py
solstar/gen_dem.py
solstar/get_tot_tbmap.py
solstar/make_spectral_cube.py
solstar/run_GHz_sun_simulator.py
solstar/simulate_chromo_TB.py
solstar/simulate_coronal_TB.py
solstar/GRFF/__init__.py
solstar/GRFF/binaries/GRFF_DEM_Transfer.so
solstar/GRFF/binaries/GRFF_DEM_Transfer_32.dll
solstar/GRFF/binaries/GRFF_DEM_Transfer_64.dll
solstar/GRFF/examples/GRFF_default_zeta.py
solstar/GRFF/examples/GRFF_user_defined_zeta.py
solstar/GRFF/source/Coulomb.cpp
solstar/GRFF/source/Coulomb.h
solstar/GRFF/source/DEM.cpp
solstar/GRFF/source/DEM.h
solstar/GRFF/source/ExtMath.cpp
solstar/GRFF/source/ExtMath.h
solstar/GRFF/source/FF.cpp
solstar/GRFF/source/FF.h
solstar/GRFF/source/GR.cpp
solstar/GRFF/source/GR.h
solstar/GRFF/source/IDLinterface.cpp
solstar/GRFF/source/IDLinterface.h
solstar/GRFF/source/MWtransfer.cpp
solstar/GRFF/source/MWtransfer.h
solstar/GRFF/source/Messages.cpp
solstar/GRFF/source/Messages.h
solstar/GRFF/source/Neutrals.cpp
solstar/GRFF/source/Neutrals.h
solstar/GRFF/source/Plasma.cpp
solstar/GRFF/source/Plasma.h
solstar/GRFF/source/PythonInterface.cpp
solstar/GRFF/source/Zeta.cpp
solstar/GRFF/source/Zeta.h
solstar/GRFF/source/dllmain.cpp
solstar/GRFF/source/getparms.cpp
solstar/GRFF/source/makefile
solstar/GRFF/source/xThermal.vcxproj
solstar/dem_python/__init__.py
solstar/dem_python/dem_inv_gsvd.py
solstar/dem_python/dem_reg_map.py
solstar/dem_python/demmap_pos.py
solstar/dem_python/dn2dem_pos.py
solstar/dem_python/data/aia_tresp_en.dat
solstar/dem_python/data/aia_tresp_en_nb.dat
solstar-0.1.3.dist-info/LICENSE
solstar-0.1.3.dist-info/METADATA
solstar-0.1.3.dist-info/WHEEL
solstar-0.1.3.dist-info/entry_points.txt
solstar-0.1.3.dist-info/top_level.txt
solstar-0.1.3.dist-info/RECORD
