Metadata-Version: 2.1
Name: solstar
Version: 0.1.3
Summary: A package to simulate GHz radio Sun spectral image cubes
Author-email: Devojyoti Kansabanik <dkansabanik@ucar.edu>
License: MIT
Project-URL: Homepage, https://github.com/devojyoti96/solstar
Classifier: Programming Language :: Python :: 3
Classifier: License :: OSI Approved :: MIT License
Classifier: Operating System :: OS Independent
Requires-Python: >=3.10
License-File: LICENSE
Requires-Dist: aiapy==0.9.1
Requires-Dist: aioftp==0.23.1
Requires-Dist: aiohappyeyeballs==2.4.3
Requires-Dist: aiohttp==3.11.8
Requires-Dist: aiosignal==1.3.1
Requires-Dist: asciitree==0.3.3
Requires-Dist: astropy==6.1.7
Requires-Dist: astropy-iers-data==0.2024.11.25.0.34.48
Requires-Dist: astropy_healpix==1.0.3
Requires-Dist: async-timeout==5.0.1
Requires-Dist: attrs==24.2.0
Requires-Dist: beautifulsoup4==4.12.3
Requires-Dist: certifi==2024.8.30
Requires-Dist: charset-normalizer==3.4.0
Requires-Dist: click==8.1.7
Requires-Dist: cloudpickle==3.1.0
Requires-Dist: contourpy==1.3.1
Requires-Dist: cycler==0.12.1
Requires-Dist: dask==2024.11.2
Requires-Dist: drms==0.8.0
Requires-Dist: fasteners==0.19
Requires-Dist: fonttools==4.55.0
Requires-Dist: frozenlist==1.5.0
Requires-Dist: fsspec==2024.10.0
Requires-Dist: h5py==3.12.1
Requires-Dist: idna==3.10
Requires-Dist: importlib_metadata==8.5.0
Requires-Dist: isodate==0.7.2
Requires-Dist: joblib==1.4.2
Requires-Dist: kiwisolver==1.4.7
Requires-Dist: locket==1.0.0
Requires-Dist: lxml==5.3.0
Requires-Dist: matplotlib==3.9.2
Requires-Dist: mpl_animators==1.2.0
Requires-Dist: multidict==6.1.0
Requires-Dist: numcodecs==0.13.1
Requires-Dist: numpy==2.1.3
Requires-Dist: packaging==24.2
Requires-Dist: pandas==2.2.3
Requires-Dist: parfive==2.1.0
Requires-Dist: partd==1.4.2
Requires-Dist: pillow==11.0.0
Requires-Dist: platformdirs==4.3.6
Requires-Dist: propcache==0.2.0
Requires-Dist: psutil==6.1.0
Requires-Dist: pyerfa==2.0.1.5
Requires-Dist: pyparsing==3.2.0
Requires-Dist: python-dateutil==2.9.0.post0
Requires-Dist: pytz==2024.2
Requires-Dist: PyYAML==6.0.2
Requires-Dist: reproject==0.14.1
Requires-Dist: requests==2.32.3
Requires-Dist: requests-file==2.1.0
Requires-Dist: requests-toolbelt==1.0.0
Requires-Dist: scipy==1.14.1
Requires-Dist: six==1.16.0
Requires-Dist: soupsieve==2.6
Requires-Dist: sunpy==6.0.3
Requires-Dist: threadpoolctl==3.5.0
Requires-Dist: toolz==1.0.0
Requires-Dist: tqdm==4.67.1
Requires-Dist: typing_extensions==4.12.2
Requires-Dist: tzdata==2024.2
Requires-Dist: urllib3==2.2.3
Requires-Dist: yarl==1.18.0
Requires-Dist: zarr==2.18.3
Requires-Dist: zeep==4.3.1
Requires-Dist: zipp==3.21.0
